{
  "paymentMethods": "Geaccepteerde methoden",
  "publishing": "Publiceren",
  "customerSms": "Klant-SMS",
  "reportsDashboard": "Dashboard",
  "reportsSales": "Verkoop",
  "reportsSalesTrend": "Trend",
  "reportsSalesSummary": "Samenvatting",
  "reportsMenuInsights": "Menu-inzichten",
  "reportsMenuInsightsCategories": "Per categorie",
  "reportsMenuInsightsItems": "Per item",
  "reportsOnlineOrdering": "Online bestellen",
  "reportsFunnel": "Website-funnel",
  "reportsClients": "Klanten",
  "reportsReservations": "Tafelreserveringen",
  "reportsGoogleRank": "Google-ranking",
  "reportsVisits": "Website-bezoeken",
  "reportsHeatmap": "Bezorg-heatmap",
  "reportsConnectivity": "Verbindingsstatus",
  "reportsPromotions": "Actiestatistieken",
  "reportsListView": "Lijstweergave",
  "reportsListOrders": "Bestellingen",
  "reportsListClients": "Klanten"
}
