{
  "marketing.home.v2.hero.title": "Vaša reštaurácia. <accent>0% provízia. 100% vaše.</accent>",
  "marketing.home.v2.hero.subtitle": "Značkové online objednávanie pre vyzdvihnutie, donášku, konzumáciu na mieste & catering — v 38 jazykoch. Nechajte si 100% z každej priamej objednávky.",
  "marketing.home.v2.hero.frameAlt": "Váš značkový obchod a lievik, ktorý mení návštevnosť z trhovísk na zákazníkov, ktorí patria vám.",
  "marketing.home.v2.hero.feat1": "0% provízia z priamych objednávok",
  "marketing.home.v2.hero.feat2": "Nechajte si 100% z každej objednávky",
  "marketing.home.v2.hero.feat3": "38 jazykov v základe",
  "marketing.home.v2.hero.feat4": "Hrdo vyrobené v Kanade"
}
