{
  "marketing.home.v2.hero.title": "ร้านอาหารของคุณ <accent>ค่าคอมมิชชัน 0% เป็นของคุณ 100%</accent>",
  "marketing.home.v2.hero.subtitle": "ระบบสั่งอาหารออนไลน์ในแบรนด์ของคุณเอง รองรับทั้งรับเอง จัดส่ง ทานที่ร้าน และจัดเลี้ยง — ใน 38 ภาษา เก็บรายได้เต็ม 100% จากทุกออร์เดอร์ตรง",
  "marketing.home.v2.hero.frameAlt": "หน้าร้านในแบรนด์ของคุณ และช่องทางที่เปลี่ยนทราฟฟิกจากมาร์เก็ตเพลสให้กลายเป็นลูกค้าที่เป็นของคุณเอง",
  "marketing.home.v2.hero.feat1": "ค่าคอมมิชชัน 0% สำหรับออร์เดอร์ตรง",
  "marketing.home.v2.hero.feat2": "เก็บรายได้เต็ม 100% จากทุกออร์เดอร์",
  "marketing.home.v2.hero.feat3": "รองรับ 38 ภาษาในตัว",
  "marketing.home.v2.hero.feat4": "สร้างสรรค์ในแคนาดาอย่างภาคภูมิ"
}
