{
  "marketing.home.v2.hero.title": "Το Εστιατόριό σας. <accent>0% Προμήθεια. 100% Δικό σας.</accent>",
  "marketing.home.v2.hero.subtitle": "Επώνυμες ηλεκτρονικές παραγγελίες για παραλαβή, διανομή, επιτόπια εστίαση & catering — σε 38 γλώσσες. Κρατήστε το 100% κάθε άμεσης παραγγελίας.",
  "marketing.home.v2.hero.frameAlt": "Η επώνυμη βιτρίνα σας και η διοχέτευση που μετατρέπει την επισκεψιμότητα των marketplace σε πελάτες που σας ανήκουν.",
  "marketing.home.v2.hero.feat1": "0% προμήθεια στις άμεσες παραγγελίες",
  "marketing.home.v2.hero.feat2": "Κρατήστε το 100% κάθε παραγγελίας",
  "marketing.home.v2.hero.feat3": "38 γλώσσες ενσωματωμένες",
  "marketing.home.v2.hero.feat4": "Με υπερηφάνεια κατασκευασμένο στον Καναδά"
}
