{
  "marketing.home.v2.softlaunch.eyebrow": "Měkký start",
  "marketing.home.v2.softlaunch.title": "Něco <accent>velkého</accent> se vaří.",
  "marketing.home.v2.softlaunch.body": "Zveme vybranou skupinu majitelů restaurací, aby se připojili včas a rostli společně s Fee Free Ordering.",
  "marketing.home.v2.softlaunch.tick1": "Buďte součástí budoucnosti online objednávání",
  "marketing.home.v2.softlaunch.tick2": "Zajistěte si výhody předčasného přístupu",
  "marketing.home.v2.softlaunch.tick3": "Pomozte utvářet platformu",
  "marketing.home.v2.softlaunch.cta": "Připojte se k měkkému startu",
  "marketing.home.v2.softlaunch.imgAlt": "Fee Free Ordering — brzy spouštíme",
  "marketing.home.v2.cards.reports.eyebrow": "Řiďte svůj podnik",
  "marketing.home.v2.cards.reports.title": "Mějte svá čísla pod kontrolou. Vlastněte své zákazníky.",
  "marketing.home.v2.cards.reports.b1": "Reporty a přehledy v reálném čase",
  "marketing.home.v2.cards.reports.b2": "Databáze a historie zákazníků",
  "marketing.home.v2.cards.reports.b3": "Nástroje pro akce a věrnostní programy",
  "marketing.home.v2.cards.reports.b4": "Exportujte svá data kdykoli",
  "marketing.home.v2.cards.app.eyebrow": "Stáhněte si aplikaci",
  "marketing.home.v2.cards.app.title": "Kitchen Order App pro váš tým.",
  "marketing.home.v2.cards.app.body": "Spravujte objednávky, tiskněte účtenky a aktualizujte stav — vše z vašeho tabletu.",
  "marketing.home.v2.cards.growth.eyebrow": "Stvořeno pro růst",
  "marketing.home.v2.cards.growth.title": "Více objednávek. Nižší poplatky. Vyšší zisky.",
  "marketing.home.v2.cards.growth.b1": "Neomezené objednávky",
  "marketing.home.v2.cards.growth.b2": "Žádné skryté poplatky",
  "marketing.home.v2.cards.growth.b3": "Žádné poplatky za zřízení",
  "marketing.home.v2.cards.growth.b4": "Zrušte kdykoli",
  "marketing.home.v2.cards.data.eyebrow": "Důvěryhodné a bezpečné",
  "marketing.home.v2.cards.data.title": "Vaše data jsou v bezpečí. Váš podnik zůstává váš.",
  "marketing.home.v2.cards.data.body": "Vaše data nikdy neprodáváme. Nikdy.",
  "marketing.home.v2.cards.data.b1": "Vaši zákazníci patří vám",
  "marketing.home.v2.cards.data.b2": "Exportujte svá data kdykoli",
  "marketing.home.v2.cards.data.b3": "Zabezpečené a šifrované",
  "marketing.home.v2.cards.data.b4": "Vyrobeno v Kanadě"
}
